verilogCode/design/mod_reg16.sv


/****** mod_reg16.sv *******/

// Inputs: 16 inputs, 8 bits each
// Outputs: 16 output, 8 bits

module mod_reg16(clk, resetn, wr_en,
                i,
                o, reg_full
                );

    localparam N = 16;
    integer index;

    input clk, resetn, wr_en;
    input [N-1:0][7:0] i;

    output reg reg_full;
    output reg [N-1:0][7:0] o;


    always @(posedge clk) //or posedge resetn)
    begin
        if(!resetn)
        begin
            reg_full = 1'b0;
            for(index=0; index < N; index=index+1)
                o[index] = 8'h00;
        end
        else if(wr_en && !reg_full)
        begin
            reg_full = 1'b1;
            for(index=0; index < N; index=index+1)
                o[index] = i[index];
        end
        else
            reg_full = 1'b0;
    end

endmodule

verilogCode/tb/tb_mod_reg16.sv



//`include "../design/mod_reg16.sv"

`timescale 1ns/10ps    // time-unit = 1 ns, precision 10 ps

module tb_mod_reg16();

    localparam N = 16;
    localparam period = 20;

    reg clk, resetn, wr_en;
    reg [(N-1):0][7:0] i;
    
    wire [(N-1):0][7:0] o;
    wire reg_full;

    integer index;

    mod_reg16 DUT(
                 .clk(clk), .resetn(resetn), .wr_en(wr_en),
                 .i(i),
                 .o(o), .reg_full(reg_full)
                 );


    always #100 clk = !clk;

    
    initial 
    begin
        $dumpfile("wv_mod_reg16.vcd");
        $dumpvars(0, tb_mod_reg16);
    
    end
    

    task enableResetn;
    begin
        // @(posedge clk)
        resetn = 1'b0;
        // @(posedge clk)
        #period resetn = 1'b1;
    end
    endtask


    task enableWrite;
    begin
        $display("Enabling write signal");
        @(posedge clk)
        #period wr_en = 1'b1;
        @(posedge clk)
        #period wr_en = 1'b0;
    end
    endtask

    task setInput;
    input reg [7:0] seed;
    begin
        i[0] = seed;
        for(index=1; index < N; index=index+1)
            i[index] = i[index-1] + 8'h01;
    end
    endtask

    task test_resetn;
    begin
        if(!resetn)
        begin
            #period;
            for(index=0; index < N; index=index+1)
            begin
                #period;
                if(o[index] == 8'h00)
                    $display("Correct value in position %d \n", o[index]);
                else
                    $display("Something not working properly. Value: %h ; Pos: %d \n", o[index], index);
            end 
        end
        //$stop;
    end
    endtask

    task test_read;
    begin
        #period;
        for(index=0; index < N; index=index+1)
        begin
            #period;
            if(i[index] == o[index])
                $display("Correct value: %h \n", o[index]);
            else
                $display("Expected value: %h ;; Value read: %h ;; Pos: %d \n", i[index], o[index], index);
        end
    end
    endtask

    initial
    begin
        clk = 1'b0;
        enableResetn;
        //test_resetn;

        setInput(8'h00);
        enableWrite;
        #period;

        test_read;

        setInput(8'h0f);
        enableWrite;
        #period;

        test_read;

        setInput(8'h10);
        enableWrite;
        #period;

        test_read;

        $finish;
    end

endmodule

Vivado_projects/reg16/reg16.sim/sim_1/behav/xsim/wv_mod_reg16.vcd
$date
   Sat Sep  4 12:43:00 2021
$end
$version
  2020.2
$end
$timescale
  1ps
$end
$scope module tb_mod_reg16 $end
$var reg 1 ! clk $end
$var reg 1 " resetn $end
$var reg 1 # wr_en $end
$var reg 128 $ i [15:0] $end
$var wire 128 % o [15:0] $end
$var wire 1 & reg_full $end
$var integer 32 ' index $end
$scope module DUT $end
$var integer 32 ( index $end
$var wire 1 ) clk $end
$var wire 1 * resetn $end
$var wire 1 + wr_en $end
$var wire 128 , i [15:0] $end
$var reg 1 - reg_full $end
$var reg 128 . o [15:0] $end
$upscope $end
$scope task enableResetn $end
$upscope $end
$scope task enableWrite $end
$upscope $end
$scope task setInput $end
$var reg 8 / seed [7:0] $end
$upscope $end
$scope task test_read $end
$upscope $end
$upscope $end
$enddefinitions $end
#0
$dumpvars
0!
0"
x#
bx $
bx %
x&
bx '
bx (
0)
0*
x+
bx ,
x-
bx .
bx /
$end
#20000
1"
b1111000011100000110100001100000010110000101000001001000010000000011100000110000001010000010000000011000000100000000100000000 $
b10000 '
1*
b1111000011100000110100001100000010110000101000001001000010000000011100000110000001010000010000000011000000100000000100000000 ,
b0 /
#100000
1!
0&
1)
0-
#120000
1#
1+
#200000
0!
0)
#300000
1!
b1111000011100000110100001100000010110000101000001001000010000000011100000110000001010000010000000011000000100000000100000000 %
1&
b10000 (
1)
1-
b1111000011100000110100001100000010110000101000001001000010000000011100000110000001010000010000000011000000100000000100000000 .
#320000
0#
0+
#360000
b0 '
#380000
b1 '
#400000
0!
b10 '
0)
#420000
b11 '
#440000
b100 '
#460000
b101 '
#480000
b110 '
#500000
1!
0&
b111 '
1)
0-
#520000
b1000 '
#540000
b1001 '
#560000
b1010 '
#580000
b1011 '
#600000
0!
b1100 '
0)
#620000
b1101 '
#640000
b1110 '
#660000
b1111 '
#680000
b11110000111010001110000011011000110100001100100011000000101110001011000010101000101000001001100010010000100010001000000001111 $
b10000 '
b11110000111010001110000011011000110100001100100011000000101110001011000010101000101000001001100010010000100010001000000001111 ,
b1111 /
#700000
1!
1)
0-
#720000
1#
1+
#800000
0!
0)
#900000
1!
b11110000111010001110000011011000110100001100100011000000101110001011000010101000101000001001100010010000100010001000000001111 %
1&
b10000 (
1)
1-
b11110000111010001110000011011000110100001100100011000000101110001011000010101000101000001001100010010000100010001000000001111 .
#920000
0#
0+
#960000
b0 '
#980000
b1 '
#1000000
0!
b10 '
0)
